{"version":"1.7.44","country_calling_codes":{"34":["ES"],"52":["MX"],"55":["BR"],"56":["CL"]},"countries":{"BR":["55","00(?:1[245]|2[1-35]|31|4[13]|[56]5|99)","(?:[1-46-9]\\d\\d|5(?:[0-46-9]\\d|5[0-24679]))\\d{8}|[1-9]\\d{9}|[3589]\\d{8}|[34]\\d{7}",[8,9,10,11],[["(\\d{4})(\\d{4})","$1-$2",["300|4(?:0[02]|37)","4(?:02|37)0|[34]00"]],["(\\d{3})(\\d{2,3})(\\d{4})","$1 $2 $3",["(?:[358]|90)0"],"0$1"],["(\\d{2})(\\d{4})(\\d{4})","$1 $2-$3",["(?:[14689][1-9]|2[12478]|3[1-578]|5[13-5]|7[13-579])[2-57]"],"($1)"],["(\\d{2})(\\d{5})(\\d{4})","$1 $2-$3",["[16][1-9]|[2-57-9]"],"($1)"]],"0",0,"0(?:(1[245]|2[1-35]|31|4[13]|[56]5|99)(\\d{10,11}))?","$2",0,0,[0,["(?:[14689][1-9]|2[12478]|3[1-578]|5[13-5]|7[13-579])(?:7|9\\d)\\d{7}",[10,11]]]],"CL":["56","(?:0|1(?:1[0-69]|2[0-57]|5[13-58]|69|7[0167]|8[018]))0","12300\\d{6}|6\\d{9,10}|[2-9]\\d{8}",[9,10,11],[["(\\d{5})(\\d{4})","$1 $2",["21"],"($1)"],["(\\d{2})(\\d{3})(\\d{4})","$1 $2 $3",["44"]],["(\\d)(\\d{4})(\\d{4})","$1 $2 $3",["2[23]"],"($1)"],["(\\d)(\\d{4})(\\d{4})","$1 $2 $3",["9[2-9]"]],["(\\d{2})(\\d{3})(\\d{4})","$1 $2 $3",["3[2-5]|[47]|5[1-3578]|6[13-57]|8(?:0[1-9]|[1-9])"],"($1)"],["(\\d{3})(\\d{3})(\\d{3,4})","$1 $2 $3",["60|8"]],["(\\d{4})(\\d{3})(\\d{4})","$1 $2 $3",["1"]],["(\\d{3})(\\d{3})(\\d{2})(\\d{3})","$1 $2 $3 $4",["60"]]],0,0,0,0,0,0,[0,["(?:2(?:1962|3(?:2\\d\\d|3(?:00|23)))|80[1-9]\\d\\d)\\d{4}|(?:22|3[2-5]|[47][1-35]|5[1-3578]|6[13-57]|8[1-9]|9[2-9])\\d{7}",[9]]]],"ES":["34","00","(?:51|[6-9]\\d)\\d{7}",[9],[["(\\d{3})(\\d{3})(\\d{3})","$1 $2 $3",["[89]00"]],["(\\d{3})(\\d{2})(\\d{2})(\\d{2})","$1 $2 $3 $4",["[5-9]"]]],0,0,0,0,0,0,[0,["9(?:6906(?:09|10)|7390\\d\\d)\\d\\d|(?:6\\d|7[1-48])\\d{7}"]]],"MX":["52","0[09]","(?:1(?:[01467]\\d|[2359][1-9]|8[1-79])|[2-9]\\d)\\d{8}",[10,11],[["(\\d{2})(\\d{4})(\\d{4})","$1 $2 $3",["33|5[56]|81"],0,1],["(\\d{3})(\\d{3})(\\d{4})","$1 $2 $3",["[2-9]"],0,1],["(\\d)(\\d{2})(\\d{4})(\\d{4})","$2 $3 $4",["1(?:33|5[56]|81)"],0,1],["(\\d)(\\d{3})(\\d{3})(\\d{4})","$2 $3 $4",["1"],0,1]],"01",0,"0(?:[12]|4[45])|1",0,0,0,[0,["(?:1(?:2(?:2[1-9]|3[1-35-8]|4[13-9]|7[1-689]|8[1-578]|9[467])|3(?:1[1-79]|[2458][1-9]|3\\d|7[1-8]|9[1-5])|4(?:1[1-57-9]|[24-7][1-9]|3[1-8]|8[1-35-9]|9[2-689])|5(?:[56]\\d|88|9[1-79])|6(?:1[2-68]|[2-4][1-9]|5[1-3689]|6[1-57-9]|7[1-7]|8[67]|9[4-8])|7(?:[1-467][1-9]|5[13-9]|8[1-69]|9[17])|8(?:1\\d|2[13-689]|3[1-6]|4[124-6]|6[1246-9]|7[1-378]|9[12479])|9(?:1[346-9]|2[1-4]|3[2-46-8]|5[1348]|[69][1-9]|7[12]|8[1-8]))|2(?:2[1-9]|3[1-35-8]|4[13-9]|7[1-689]|8[1-578]|9[467])|3(?:1[1-79]|[2458][1-9]|3\\d|7[1-8]|9[1-5])|4(?:1[1-57-9]|[24-7][1-9]|3[1-8]|8[1-35-9]|9[2-689])|5(?:[56]\\d|88|9[1-79])|6(?:1[2-68]|[2-4][1-9]|5[1-3689]|6[1-57-9]|7[1-7]|8[67]|9[4-8])|7(?:[1-467][1-9]|5[13-9]|8[1-69]|9[17])|8(?:1\\d|2[13-689]|3[1-6]|4[124-6]|6[1246-9]|7[1-378]|9[12479])|9(?:1[346-9]|2[1-4]|3[2-46-8]|5[1348]|[69][1-9]|7[12]|8[1-8]))\\d{7}"]],"00"]},"nonGeographic":{}}